[{"_id":"123455","comment":"A good book but definitely I don't like many parts of the plot","rate":3,"elementId":"5d318e1a8541744830bef139","createdAt":"2019-08-01T12:46:45.895Z"},{"comment":"A good book but definitely I don't like many parts of the plot","rate":5,"elementId":"5d318e1a8541744830bef139","_id":"68xspwkc61kvrh"},{"comment":"A good book but definitely I don't like many parts of the plot","rate":7,"elementId":"5d318e1a8541744830bef139","_id":"68xn9ckc61udvf"},{"comment":"A good book but definitely I don't like many parts of the plot","rate":5,"elementId":"5d318e1a8541744830bef139","_id":"68xm2kkc61wxlf"},{"comment":"A good book but definitely I don't like many parts of the plot","rate":5,"elementId":"tt0167260","_id":"68xs5kkc62ax5w"}]
